pinboard/__init__.py
pinboard/exceptions.py
pinboard/metadata.py
pinboard/pinboard.py
pinboard-2.1.9.data/scripts/pinboard
pinboard-2.1.9.dist-info/LICENSE
pinboard-2.1.9.dist-info/METADATA
pinboard-2.1.9.dist-info/NOTICE
pinboard-2.1.9.dist-info/WHEEL
pinboard-2.1.9.dist-info/top_level.txt
pinboard-2.1.9.dist-info/RECORD
