Metadata-Version: 2.1
Name: pinboard
Version: 2.1.9
Summary: A Python wrapper for Pinboard.in
Home-page: http://github.com/lionheart/pinboard.py
Author: Dan Loewenherz
Author-email: dan@lionheartsw.com
License: Apache 2.0
Keywords: pinboard
Classifier: Development Status :: 5 - Production/Stable
Classifier: Environment :: Console
Classifier: Intended Audience :: Developers
Classifier: Natural Language :: English
Classifier: Operating System :: OS Independent
Classifier: Programming Language :: Python
Classifier: Programming Language :: Python :: 2.7
Classifier: Programming Language :: Python :: 3.5
Classifier: Programming Language :: Python :: 3.6
Classifier: Programming Language :: Python :: 3.7
Classifier: Topic :: Software Development :: Libraries :: Python Modules
Classifier: Topic :: Internet :: WWW/HTTP :: Dynamic Content :: CGI Tools/Libraries
Classifier: Topic :: Utilities
Classifier: License :: OSI Approved :: Apache Software License
License-File: LICENSE
License-File: NOTICE
